tbase_config/__init__.py
tbase_config/admin.py
tbase_config/apps.py
tbase_config/models.py
tbase_config/tests.py
tbase_config/views.py
django_tbase_config-2023.5.2016845975.dist-info/METADATA
django_tbase_config-2023.5.2016845975.dist-info/WHEEL
django_tbase_config-2023.5.2016845975.dist-info/top_level.txt
django_tbase_config-2023.5.2016845975.dist-info/RECORD
