Metadata-Version: 2.1
Name: django-tbase-config
Version: 2023.5.2016845975
Summary: Terry django base config ,
Home-page: https://terrychanorg.jetbrains.space/p/django-expand/repositories/tbase_config/files/README.md
Author: Terry Chan
Author-email: napoler2008@gmail.com
Requires-Dist: django-solo (==2.0.0)
